finecode_jsonrpc/__init__.py
finecode_jsonrpc/_io_thread.py
finecode_jsonrpc/client.py
finecode_jsonrpc/py.typed
finecode_jsonrpc/lsp/__init__.py
finecode_jsonrpc-0.1.0a1.dist-info/METADATA
finecode_jsonrpc-0.1.0a1.dist-info/WHEEL
finecode_jsonrpc-0.1.0a1.dist-info/top_level.txt
finecode_jsonrpc-0.1.0a1.dist-info/RECORD
