Metadata-Version: 2.4
Name: finecode_jsonrpc
Version: 0.1.0a1
Summary: JSON-RPC client implementation for FineCode
Author-email: Vladyslav Hnatiuk <aders1234@gmail.com>
Requires-Python: >=3.11
Requires-Dist: loguru==0.7.*
Requires-Dist: culsans==0.9.*
Requires-Dist: apischema==0.19.*
Dynamic: requires-python
